qBitrr/__init__.py
qBitrr/arr_tables.py
qBitrr/arss.py
qBitrr/bundled_data.py
qBitrr/config.py
qBitrr/env_config.py
qBitrr/errors.py
qBitrr/ffprobe.py
qBitrr/gen_config.py
qBitrr/home_path.py
qBitrr/logger.py
qBitrr/main.py
qBitrr/tables.py
qBitrr/utils.py
qBitrr-2.6.0.dist-info/LICENSE
qBitrr-2.6.0.dist-info/METADATA
qBitrr-2.6.0.dist-info/WHEEL
qBitrr-2.6.0.dist-info/entry_points.txt
qBitrr-2.6.0.dist-info/top_level.txt
qBitrr-2.6.0.dist-info/RECORD
