Metadata-Version: 2.1
Name: qBitrr
Version: 2.6.0
Summary: A simple script to monitor Qbit and communicate with Radarr and Sonarr
Home-page: https://github.com/Drapersniper/Qbitrr
Author: Draper
Author-email: draper@draper.wtf
License: MIT
Project-URL: Discord Server, https://discord.gg/FT3puape2A
Project-URL: Issue Tracker, https://github.com/Drapersniper/Qbitrr/issues
Project-URL: Source Code, https://github.com/Drapersniper/Qbitrr
Classifier: Development Status :: 5 - Production/Stable
Classifier: Intended Audience :: Developers
Classifier: Intended Audience :: End Users/Desktop
Classifier: License :: OSI Approved :: MIT License
Classifier: Natural Language :: English
Classifier: Operating System :: MacOS :: MacOS X
Classifier: Operating System :: Microsoft :: Windows
Classifier: Operating System :: POSIX :: Linux
Classifier: Programming Language :: Python :: 3 :: Only
Classifier: Programming Language :: Python :: 3.8
Classifier: Programming Language :: Python :: 3.9
Classifier: Programming Language :: Python :: 3.10
Classifier: Programming Language :: Python :: Implementation :: CPython
Classifier: Programming Language :: Python :: Implementation :: PyPy
Classifier: Topic :: Terminals
Classifier: Topic :: Utilities
Classifier: Typing :: Typed
Requires-Python: <4,>=3.8.1
License-File: LICENSE
Requires-Dist: cachetools (==4.2.4)
Requires-Dist: colorama (==0.4.4)
Requires-Dist: coloredlogs (==15.0.1)
Requires-Dist: environ-config (==21.2.0)
Requires-Dist: ffmpeg-python (==0.2.0)
Requires-Dist: jaraco.docker (==2.0)
Requires-Dist: packaging (==21.3)
Requires-Dist: pathos (==0.2.8)
Requires-Dist: peewee (==3.14.7)
Requires-Dist: ping3 (==3.0.2)
Requires-Dist: pyarr (==2.0.6)
Requires-Dist: qbittorrent-api (==2022.8.38)
Requires-Dist: requests (==2.26.0)
Requires-Dist: tomlkit (==0.7.2)
Provides-Extra: all
Requires-Dist: black (==22.1.0) ; extra == 'all'
Requires-Dist: bump2version (==1.0.1) ; extra == 'all'
Requires-Dist: isort (==5.10.1) ; extra == 'all'
Requires-Dist: pip-tools (==6.4.0) ; extra == 'all'
Requires-Dist: pre-commit (==2.17.0) ; extra == 'all'
Requires-Dist: pyinstaller (==4.8) ; extra == 'all'
Requires-Dist: pyupgrade (==2.31.0) ; extra == 'all'
Requires-Dist: twine (==3.7.1) ; extra == 'all'
Requires-Dist: ujson (==5.4.0) ; extra == 'all'
Provides-Extra: dev
Requires-Dist: black (==22.1.0) ; extra == 'dev'
Requires-Dist: bump2version (==1.0.1) ; extra == 'dev'
Requires-Dist: isort (==5.10.1) ; extra == 'dev'
Requires-Dist: pip-tools (==6.4.0) ; extra == 'dev'
Requires-Dist: pre-commit (==2.17.0) ; extra == 'dev'
Requires-Dist: pyinstaller (==4.8) ; extra == 'dev'
Requires-Dist: pyupgrade (==2.31.0) ; extra == 'dev'
Requires-Dist: twine (==3.7.1) ; extra == 'dev'
Requires-Dist: ujson (==5.4.0) ; extra == 'dev'
Provides-Extra: fast
Requires-Dist: ujson (==5.4.0) ; extra == 'fast'
